nbtoolbox/__init__.py
nbtoolbox/version.py
nbtoolbox-0.0.1.dist-info/LICENSE
nbtoolbox-0.0.1.dist-info/METADATA
nbtoolbox-0.0.1.dist-info/WHEEL
nbtoolbox-0.0.1.dist-info/entry_points.txt
nbtoolbox-0.0.1.dist-info/top_level.txt
nbtoolbox-0.0.1.dist-info/RECORD
