Metadata-Version: 2.1
Name: nbtoolbox
Version: 0.0.1
Summary: Jupyter notebook tools collection.
Home-page: https://github.com/ayasyrev/nbtoolbox
Author: Yasyrev Andrei
Author-email: a.yasyrev@gmail.com
License: apache2
Classifier: Programming Language :: Python :: 3.8
Classifier: Programming Language :: Python :: 3.9
Classifier: Programming Language :: Python :: 3.10
Classifier: Programming Language :: Python :: 3.11
Classifier: Programming Language :: Python :: 3.12
Classifier: License :: OSI Approved :: Apache Software License
Classifier: Operating System :: OS Independent
License-File: LICENSE
Provides-Extra: test
